{
    "widgets": [{
        "name": "rock-my-todos",
        "nonClosable": false,
        "nonMaximizable": true,
        "nonDraggable": false,
        "iconButtons": "",
        "config": {
            "heading": "My To Do's",
            "headerIcon": "icons:assignment",
            "component": {
                "name": "rock-my-todos",
                "path": "../../rock-my-todos/rock-my-todos.html"
            }
        }
    }, {
        "name": "rock-my-todos",
        "nonClosable": false,
        "nonMaximizable": false,
        "nonDraggable": false,
        "iconButtons": "",
        "config": {
            "heading": "My To Do's",
            "headerIcon": "icons:assignment",
            "component": {
                "name": "rock-my-todos",
                "path": "../../rock-my-todos/rock-my-todos.html"
            }
        }
    }, {
        "name": "rock-my-todos",
        "nonClosable": false,
        "nonMaximizable": true,
        "nonDraggable": false,
        "iconButtons": "",
        "config": {
            "heading": "My To Do's",
            "headerIcon": "icons:assignment",
            "component": {
                "name": "rock-my-todos",
                "path": "../../rock-my-todos/rock-my-todos.html"
            }
        }
    }]
}