{
    "completionPercentage": 65,
    "tofixes": [
                 {                    
                    "data": {        
                             "name": "brandext",
                             "type": "warning",                                
                             "label": "Brand Extension not available",                                
                             "eventName": "tofixtap"
                             }
                 },
                 {                    
                     "data": {        
                             "name": "priceissue",
                             "type": "warning",                                
                             "label": "Canada price not available",                                
                             "eventName": "tofixtap"
                             }
                 },                 
                 {                    
                     "data": {        
                             "name": "msrpissue",
                             "type": "error",                                
                             "label": "Incorrect MSRP",                                
                             "eventName": "tofixtap"
                             }
                 },
                 {                    
                     "data": {        
                             "name": "missingvideo1",
                             "type": "information",                                
                             "label": "Missing videos",                                
                             "eventName": "tofixtap"
                             }
                 },
                 {                    
                     "data": {        
                             "name": "missingvideo2",
                             "type": "information",                                
                             "label": "Missing videos",                                
                             "eventName": "tofixtap"
                             }
                 }    
          ]
 }