{
    "config": {
        "viewMode": "Tabular",
        "isMultiSelect": true
    },
    "tabular": {
        "columns": [
            {
                "header": "Short Name",
                "name": "shortName",
                "sortable": true,
                "filterable": false,
                "editType":"text"
            },
            {
                "header": "Long Name",
                "name": "longName",
                "sortable": false,
                "filterable": true,
                "editType":""
            },
            {
                "header": "Product Type",
                "name": "productType",
                "sortable": false,
                "filterable": false,
                "editType":"text"
            },
            {
                "header": "Description",
                "name": "description",
                "sortable": true,
                "filterable": false,
                "editType":"textarea"

            },
            {
                "header": "Is New",
                "name": "isNew",
                "sortable": false,
                "filterable": false,
                "editType":"checkbox"
            }
        ]
    },
    "dataItems": [
       
        {
            "shortName": "web Price",
            "longName": "Web Price",
            "productType": "Electronics",
            "description": "product web price",
            "isNew": false,
            "isApproved": true
        },
        {
            "shortName": "catalog",
            "longName": "Catalog",
            "productType": "Toys",
            "description": "catalog information",
            "isNew": true,
            "isApproved": false
        },
        {
            "shortName": "cost",
            "longName": "Cost",
            "productType": "Value",
            "description": "cost of the product",
            "isNew": false,
            "isApproved": true
        },
        {
            "shortName": "cost",
            "longName": "Cost",
            "productType": "Value",
            "description": "cost of the product",
            "isNew": false,
            "isApproved": true
        },
        {
            "shortName": "cost",
            "longName": "Cost",
            "productType": "Value",
            "description": "cost of the product",
            "isNew": false,
            "isApproved": true
        }
    ]
}